appledict2semantic/__init__.py
appledict2semantic/main.py
appledict2semantic/helpers/__init__.py
appledict2semantic/helpers/class_check.py
appledict2semantic/helpers/cleanup.py
appledict2semantic/helpers/io_utils.py
appledict2semantic/helpers/process_definition_phrases.py
appledict2semantic/helpers/process_html.py
appledict2semantic/helpers/process_main_definition.py
appledict2semantic/helpers/span_converters.py
appledict2semantic/helpers/wrapinbrackets.py
appledict2semantic-1.3.1.dist-info/METADATA
appledict2semantic-1.3.1.dist-info/WHEEL
appledict2semantic-1.3.1.dist-info/entry_points.txt
appledict2semantic-1.3.1.dist-info/licenses/LICENSE
appledict2semantic-1.3.1.dist-info/RECORD
