Metadata-Version: 2.4
Name: appledict2semantic
Version: 1.3.1
Summary: Convert Apple Dictionary HTML `<span>`s into semantic, readable HTML. Removes the dependency on CSS styles by converting span class names into appropriate semantic HTML tags and structural markup.
Project-URL: Homepage, https://github.com/yell0wsuit/appledict2semantic
Project-URL: Issues, https://github.com/yell0wsuit/appledict2semantic/issues
Project-URL: Changelog, https://github.com/yell0wsuit/appledict2semantic/blob/main/changelog.md
Author: yell0wsuit
License-Expression: MIT
License-File: LICENSE
Classifier: Operating System :: OS Independent
Classifier: Programming Language :: Python :: 3
Requires-Python: >=3.10
Requires-Dist: beautifulsoup4
Requires-Dist: lxml
Requires-Dist: tqdm
